eimantas_data_transformations/__init__.py
eimantas_data_transformations/transformations.py
eimantas_data_transformations-0.1.1.dist-info/METADATA
eimantas_data_transformations-0.1.1.dist-info/WHEEL
eimantas_data_transformations-0.1.1.dist-info/RECORD
