Metadata-Version: 2.1
Name: eimantas_data_transformations
Version: 0.1.1
Summary: A Python library for data transformations
License: MIT
Author: Eimantas Venslovas
Requires-Python: >=3.12,<4.0
Classifier: License :: OSI Approved :: MIT License
Classifier: Programming Language :: Python :: 3
Classifier: Programming Language :: Python :: 3.12
Requires-Dist: numpy (>=2.0.0,<3.0.0)
